mappa/__init__.py
mappa/mappa.py
mappaforterminal-0.1.0.dist-info/METADATA
mappaforterminal-0.1.0.dist-info/WHEEL
mappaforterminal-0.1.0.dist-info/entry_points.txt
mappaforterminal-0.1.0.dist-info/top_level.txt
mappaforterminal-0.1.0.dist-info/RECORD
