Metadata-Version: 2.2
Name: mappaforterminal
Version: 0.1.0
Summary: A voice-controlled terminal assistant
Home-page: https://github.com/yourusername/mappa
Author: Your Name
Classifier: Programming Language :: Python :: 3
Classifier: License :: OSI Approved :: MIT License
Classifier: Operating System :: OS Independent
Requires-Python: >=3.7
Requires-Dist: speechrecognition
Requires-Dist: pyttsx3
Requires-Dist: requests
Requires-Dist: torch
Requires-Dist: transformers
Requires-Dist: python-dotenv
Dynamic: author
Dynamic: classifier
Dynamic: home-page
Dynamic: requires-dist
Dynamic: requires-python
Dynamic: summary
